README.md
setup.cfg
setup.py
pearsondictionary/__init__.py
pearsondictionary/code.py
pearsondictionary/tests.py
pearsondictionary.egg-info/PKG-INFO
pearsondictionary.egg-info/SOURCES.txt
pearsondictionary.egg-info/dependency_links.txt
pearsondictionary.egg-info/not-zip-safe
pearsondictionary.egg-info/top_level.txt