Metadata-Version: 1.0
Name: pearsondictionary
Version: 0.2
Summary: Simple wrapper for Pearson Dictionaries API
Home-page: https://github.com/57uff3r/pearsondictionary
Author: Andrey Korchak
Author-email: 57uff3r@gmail.com
License: MIT
Platform: UNKNOWN
